memobird.py
memobird-0.1.1.dist-info/DESCRIPTION.rst
memobird-0.1.1.dist-info/METADATA
memobird-0.1.1.dist-info/RECORD
memobird-0.1.1.dist-info/WHEEL
memobird-0.1.1.dist-info/metadata.json
memobird-0.1.1.dist-info/top_level.txt
