Metadata-Version: 2.0
Name: memobird
Version: 0.1.1
Summary: Memobird Python SDK
Home-page: https://github.com/wong2/memobird.py
Author: wong2
Author-email: wonderfuly@gmail.com
License: MIT
Keywords: memobird
Platform: UNKNOWN
Classifier: Development Status :: 4 - Beta
Classifier: Intended Audience :: Developers
Classifier: License :: OSI Approved :: MIT License
Classifier: Programming Language :: Python
Classifier: Programming Language :: Python :: 2.6
Classifier: Programming Language :: Python :: 2.7
Classifier: Programming Language :: Python :: 3.3
Classifier: Programming Language :: Python :: 3.4
Classifier: Programming Language :: Python :: 3.5
Requires-Dist: Pillow (==3.2.0)
Requires-Dist: requests (==2.9.1)
